ssrs/__init__.py
ssrs/__main__.py
ssrs/ssrs.py
ssrs-0.1.3.dist-info/METADATA
ssrs-0.1.3.dist-info/WHEEL
ssrs-0.1.3.dist-info/entry_points.txt
ssrs-0.1.3.dist-info/RECORD
